labManager/client.py
labmanager_client-1.0.5.dist-info/METADATA
labmanager_client-1.0.5.dist-info/WHEEL
labmanager_client-1.0.5.dist-info/licenses/LICENSE
labmanager_client-1.0.5.dist-info/RECORD
